LICENSE
README.md
setup.py
kard_private_api/__init__.py
kard_private_api/app.py
kard_private_api/graphql.py
kard_private_api/settings.py
kard_private_api/utils.py
kard_private_api/kard/__init__.py
kard_private_api/kard/exceptions.py
kard_private_api/kard/karder/__init__.py
kard_private_api/kard/karder/bankAccount.py
kard_private_api/kard/karder/beneficiaries.py
kard_private_api/kard/karder/beneficiary.py
kard_private_api/kard/karder/cards.py
kard_private_api/kard/karder/cashback.py
kard_private_api/kard/karder/contact.py
kard_private_api/kard/karder/contacts.py
kard_private_api/kard/karder/details.py
kard_private_api/kard/karder/family.py
kard_private_api/kard/karder/kyc.py
kard_private_api/kard/karder/notifications.py
kard_private_api/kard/karder/offers.py
kard_private_api/kard/karder/subscription.py
kard_private_api/kard/karder/topupCard.py
kard_private_api/kard/karder/topupCards.py
kard_private_api/kard/karder/transactions.py
kard_private_api/kard/karder/vault.py
kard_private_api/kard/karder/vaults.py
pyKard.egg-info/PKG-INFO
pyKard.egg-info/SOURCES.txt
pyKard.egg-info/dependency_links.txt
pyKard.egg-info/requires.txt
pyKard.egg-info/top_level.txt