Metadata-Version: 2.1
Name: pyKard
Version: 3.0.1
Summary: Python wrapper for Kard's private API
Home-page: https://github.com/ghrlt/py-kard
Author: Gaëtan Hérault
Author-email: dev@ghr.lt
License: UNKNOWN
Project-URL: Developer website, https://ghr.lt
Project-URL: Bug Tracker, https://github.com/ghrlt/py-kard/issues
Platform: UNKNOWN
Classifier: Programming Language :: Python :: 3
Classifier: License :: OSI Approved :: GNU General Public License v3 (GPLv3)
Classifier: Operating System :: OS Independent
Requires-Python: >=3.6
License-File: LICENSE
